py_fatigue/__init__.py
py_fatigue/py.typed
py_fatigue/styling.py
py_fatigue/testing.py
py_fatigue/utils.py
py_fatigue/version.py
py_fatigue/cycle_count/__init__.py
py_fatigue/cycle_count/cycle_count.py
py_fatigue/cycle_count/histogram.py
py_fatigue/cycle_count/py.typed
py_fatigue/cycle_count/rainflow.py
py_fatigue/cycle_count/utils.py
py_fatigue/damage/__init__.py
py_fatigue/damage/crack_growth.py
py_fatigue/damage/py.typed
py_fatigue/damage/stress_life.py
py_fatigue/geometry/__init__.py
py_fatigue/geometry/cylinder.py
py_fatigue/geometry/generic.py
py_fatigue/geometry/py.typed
py_fatigue/material/__init__.py
py_fatigue/material/crack_growth_curve.py
py_fatigue/material/py.typed
py_fatigue/material/sn_curve.py
py_fatigue/mean_stress/__init__.py
py_fatigue/mean_stress/corrections.py
py_fatigue/mean_stress/mean_stress.py
py_fatigue/mean_stress/py.typed
py_fatigue/stress_range/__init__.py
py_fatigue/stress_range/py.typed
py_fatigue/stress_range/stress_range.py
py_fatigue-2.1.0.dist-info/licenses/LICENSE
py_fatigue-2.1.0.dist-info/WHEEL
py_fatigue-2.1.0.dist-info/METADATA
py_fatigue-2.1.0.dist-info/RECORD
