Metadata-Version: 2.4
Name: py_fatigue
Version: 2.1.0
Summary: Py-fatigue bundles the main functionality for performing cyclic stress (fatigue) analysis and cycle-counting.
Author-email: Pietro D'Antuono <pietro.dantuono@vub.be>, Wout Weijtjens <wout.weijtjens@vub.be>
Requires-Python: >=3.10,<3.14
Classifier: Development Status :: 5 - Production/Stable
Classifier: Environment :: Console
Classifier: Intended Audience :: Science/Research
Classifier: Intended Audience :: Information Technology
Classifier: License :: OSI Approved :: GNU General Public License v3 (GPLv3)
Classifier: Natural Language :: English
Classifier: Operating System :: POSIX :: Linux
Classifier: Programming Language :: Python :: 3
Classifier: Programming Language :: Python :: 3.8
Classifier: Programming Language :: Python :: 3.9
Classifier: Programming Language :: Python :: 3.10
Classifier: Programming Language :: Python :: 3.11
Classifier: Programming Language :: Python :: 3.12
Classifier: Programming Language :: Python :: 3.13
Classifier: Topic :: Database
License-File: LICENSE
Requires-Dist: numpy>=1.24
Requires-Dist: plotly
Requires-Dist: pandas>2.2
Requires-Dist: numba>=0.61,<0.62
Requires-Dist: matplotlib
Requires-Dist: pydantic<3.0.0
Project-URL: Bug Tracker, https://github.com/owi-lab/py_fatigue/issues
Project-URL: Change Log, https://github.com/owi-lab/py_fatigue/blob/main/CHANGELOG.md
Project-URL: Organisation Homepage, https://www.owi-lab.be/
Project-URL: documentation, https://owi-lab.github.io/py_fatigue
Project-URL: homepage, https://github.com/owi-lab/py_fatigue
